dotstow/__init__.py
dotstow/__main__.py
dotstow/logger.yml
dotstow/controllers/__init__.py
dotstow/controllers/base.py
dotstow/controllers/sync.py
dotstow/services/__init__.py
dotstow/services/git.py
dotstow/services/stow.py
dotstow/services/util.py
dotstow-0.1.5.dist-info/LICENSE
dotstow-0.1.5.dist-info/METADATA
dotstow-0.1.5.dist-info/WHEEL
dotstow-0.1.5.dist-info/entry_points.txt
dotstow-0.1.5.dist-info/top_level.txt
dotstow-0.1.5.dist-info/RECORD
