Metadata-Version: 2.1
Name: dotstow
Version: 0.1.5
Summary: Manage dotfiles with stow
Home-page: https://github.com/codejamninja/dotstow
Author: Jam Risser
Author-email: jam@codejam.ninja
License: MIT
Keywords: ubuntu remaster fork install linux
Platform: UNKNOWN
Classifier: Development Status :: 4 - Beta
Classifier: Intended Audience :: Developers
Classifier: Topic :: Utilities
Classifier: License :: OSI Approved :: MIT License
Classifier: Programming Language :: Python :: 2
Classifier: Programming Language :: Python :: 2.7
Classifier: Programming Language :: Python :: 3
Classifier: Programming Language :: Python :: 3.3
Classifier: Programming Language :: Python :: 3.4
Classifier: Programming Language :: Python :: 3.5
Requires-Dist: backports.shutil-get-terminal-size (==1.0.0)
Requires-Dist: blessings (==1.6.1)
Requires-Dist: cement (==2.10.12)
Requires-Dist: cfoundation (==0.2.2)
Requires-Dist: colorama (==0.3.9)
Requires-Dist: cursor (==1.2.0)
Requires-Dist: enum34 (==1.1.6)
Requires-Dist: gitdb2 (==2.0.3)
Requires-Dist: GitPython (==2.1.10)
Requires-Dist: halo (==0.0.12)
Requires-Dist: inquirer (==2.2.0)
Requires-Dist: log-symbols (==0.0.11)
Requires-Dist: munch (==2.3.2)
Requires-Dist: pydash (==4.5.0)
Requires-Dist: pyyaml (>=4.2b1)
Requires-Dist: readchar (==0.7)
Requires-Dist: six (==1.11.0)
Requires-Dist: smmap2 (==2.0.3)
Requires-Dist: spinners (==0.0.19)
Requires-Dist: termcolor (==1.1.0)
